iflow_mcp_web_eval_agent-0.1.1.dist-info/licenses/LICENSE
webEvalAgent/__init__.py
webEvalAgent/mcp_server.py
webEvalAgent/src/__init__.py
webEvalAgent/src/agent_overlay.js
webEvalAgent/src/api_utils.py
webEvalAgent/src/browser_manager.py
webEvalAgent/src/browser_utils.py
webEvalAgent/src/env_utils.py
webEvalAgent/src/log_server.py
webEvalAgent/src/prompts.py
webEvalAgent/src/tool_handlers.py
webEvalAgent/src/utils.py
webEvalAgent/templates/static/index.html
iflow_mcp_web_eval_agent-0.1.1.dist-info/METADATA
iflow_mcp_web_eval_agent-0.1.1.dist-info/WHEEL
iflow_mcp_web_eval_agent-0.1.1.dist-info/entry_points.txt
iflow_mcp_web_eval_agent-0.1.1.dist-info/top_level.txt
iflow_mcp_web_eval_agent-0.1.1.dist-info/RECORD
