Metadata-Version: 2.4
Name: iflow-mcp_web-eval-agent
Version: 0.1.1
Summary: Operative AI - WebAgentEval Agent
Requires-Python: >=3.11
License-File: LICENSE
Requires-Dist: browser-use==0.1.40
Requires-Dist: google-genai>=1.7.0
Requires-Dist: google-generativeai>=0.8.4
Requires-Dist: langchain>=0.3.21
Requires-Dist: langchain-anthropic>=0.3.3
Requires-Dist: langchain-google-genai>=2.0.10
Requires-Dist: mcp==1.6.0
Requires-Dist: python-dotenv>=1.1.0
Requires-Dist: playwright>=1.41.0
Requires-Dist: flask>=3.1.0
Requires-Dist: flask-socketio>=5.5.1
Requires-Dist: ruff>=0.11.9
Dynamic: license-file
